LICENSE
MANIFEST.in
mysqlfuncsmodule.c
pavement.py
paver-minilib.zip
setup.py
mysqlfuncs.egg-info/PKG-INFO
mysqlfuncs.egg-info/SOURCES.txt
mysqlfuncs.egg-info/dependency_links.txt
mysqlfuncs.egg-info/top_level.txt